__init__.py
easylogger.py
myasdelogger-0.1.1.dist-info/RECORD
myasdelogger-0.1.1.dist-info/metadata.json
myasdelogger-0.1.1.dist-info/WHEEL
myasdelogger-0.1.1.dist-info/DESCRIPTION.rst
myasdelogger-0.1.1.dist-info/top_level.txt
myasdelogger-0.1.1.dist-info/METADATA
