Metadata-Version: 2.0
Name: myasdelogger
Version: 0.1.1
Summary: easylogger for easyspider
Home-page: UNKNOWN
Author: zhang1Tian
Author-email: hhczy1003@gmail.com
License: MIT License
Keywords: log,logger
Platform: any
